odoo/addons/sale_commitment_date_mandatory/README.rst
odoo/addons/sale_commitment_date_mandatory/__init__.py
odoo/addons/sale_commitment_date_mandatory/__manifest__.py
odoo/addons/sale_commitment_date_mandatory/i18n/sale_commitment_date_mandatory.pot
odoo/addons/sale_commitment_date_mandatory/models/__init__.py
odoo/addons/sale_commitment_date_mandatory/models/sale_order.py
odoo/addons/sale_commitment_date_mandatory/readme/CONTRIBUTORS.rst
odoo/addons/sale_commitment_date_mandatory/readme/DESCRIPTION.rst
odoo/addons/sale_commitment_date_mandatory/static/description/icon.png
odoo/addons/sale_commitment_date_mandatory/static/description/index.html
odoo/addons/sale_commitment_date_mandatory/views/sale_views.xml
odoo14_addon_sale_commitment_date_mandatory-14.0.1.0.1.dist-info/METADATA
odoo14_addon_sale_commitment_date_mandatory-14.0.1.0.1.dist-info/WHEEL
odoo14_addon_sale_commitment_date_mandatory-14.0.1.0.1.dist-info/top_level.txt
odoo14_addon_sale_commitment_date_mandatory-14.0.1.0.1.dist-info/RECORD
